youseedee/__init__.py
youseedee/__main__.py
youseedee-0.7.0.dist-info/METADATA
youseedee-0.7.0.dist-info/WHEEL
youseedee-0.7.0.dist-info/entry_points.txt
youseedee-0.7.0.dist-info/top_level.txt
youseedee-0.7.0.dist-info/RECORD
