Metadata-Version: 2.4
Name: youseedee
Version: 0.7.0
Summary: Interface to the latest version of the Unicode Character Database
Author-email: Simon Cozens <simon@simon-cozens.org>
License: # youseedee: interface to the UCD"
Project-URL: homepage, https://pypi.org/project/youseedee
Project-URL: repository, https://github.com/simoncozens/youseedee
Requires-Dist: requests
Requires-Dist: filelock
Requires-Dist: platformdirs>=4.3
